translator/__init__.py
cloud_translator-1.0.dist-info/LICENSE
cloud_translator-1.0.dist-info/METADATA
cloud_translator-1.0.dist-info/WHEEL
cloud_translator-1.0.dist-info/top_level.txt
cloud_translator-1.0.dist-info/RECORD
