Metadata-Version: 2.1
Name: cloud-translator
Version: 1.0
Summary: Use the same api to call the third party translator apis, such as google, tencent, baidu.
Home-page: https://github.com/yimian/cloud-translator.git
Author: yimian group
Author-email: data@yimian.com.cn
License: UNKNOWN
Platform: UNKNOWN
Classifier: Programming Language :: Python :: 3
Classifier: License :: OSI Approved :: MIT License
Classifier: Operating System :: OS Independent
Requires-Python: >=3.6
Requires-Dist: googletrans
Requires-Dist: requests
